super_cc/__init__.py
super_cc/cli.py
super_cc/installer.py
super_cc/integration.py
super_cc/validation.py
super_cc/templates/.claude/.gitignore
super_cc/templates/.claude/settings.local.json
super_cc/templates/.claude/agents/architect.md
super_cc/templates/.claude/agents/cache-manager.md
super_cc/templates/.claude/agents/context-synth.md
super_cc/templates/.claude/agents/debugger.md
super_cc/templates/.claude/agents/documenter.md
super_cc/templates/.claude/agents/incremental-analyzer.md
super_cc/templates/.claude/agents/planner.md
super_cc/templates/.claude/agents/reviewer.md
super_cc/templates/.claude/agents/tester.md
super_cc/templates/.claude/agents/workflow-orchestrator.md
super_cc/templates/.claude/cache/cache-manifest.json
super_cc/templates/.claude/cache/invalidation-rules.yaml
super_cc/templates/.claude/cache/last-analysis-commit
super_cc/templates/.claude/commands/agent-status.md
super_cc/templates/.claude/commands/cache-optimize.md
super_cc/templates/.claude/commands/cache-status.md
super_cc/templates/.claude/commands/cache-test.md
super_cc/templates/.claude/commands/context-synth.md
super_cc/templates/.claude/commands/context.md
super_cc/templates/.claude/commands/eco-mode.md
super_cc/templates/.claude/commands/revert.md
super_cc/templates/.claude/commands/review.md
super_cc/templates/.claude/commands/tdd.md
super_cc/templates/.claude/commands/token-usage.md
super_cc/templates/.claude/commands/workflow.md
super_cc/templates/.claude/context/last-build-commit
super_cc/templates/.claude/context/summaries/_claude_agents_planner_md_summary.json
super_cc/templates/.claude/context/summaries/_claude_commands_tdd_md_summary.json
super_cc/templates/.claude/context/summaries/_claude_hooks_pre_tool_use_sh_summary.json
super_cc/templates/.claude/context/summaries/docs_Super_CC_Architecture_md_summary.json
super_cc/templates/.claude/hooks/post_tool_use.sh
super_cc/templates/.claude/hooks/pre_tool_use.sh
super_cc/templates/.claude/logs/tools.log
super_cc-1.0.2.dist-info/METADATA
super_cc-1.0.2.dist-info/WHEEL
super_cc-1.0.2.dist-info/entry_points.txt
super_cc-1.0.2.dist-info/licenses/LICENSE
super_cc-1.0.2.dist-info/RECORD
