Metadata-Version: 2.4
Name: super-cc
Version: 1.0.2
Summary: Transform any repository with Claude Code into a high-productivity dev envrionment
Project-URL: Homepage, https://github.com/xanderhnasko/superclaude
Project-URL: Documentation, https://github.com/xanderhnasko/superclaude#readme
Project-URL: Repository, https://github.com/xanderhnasko/superclaude
Project-URL: Issues, https://github.com/xanderhnasko/superclaude/issues
Author: Xander Hnasko
License: MIT License
License-File: LICENSE
Keywords: agents,ai,automation,claude,development,subagents,workflow
Classifier: Development Status :: 5 - Production/Stable
Classifier: Environment :: Console
Classifier: Intended Audience :: Developers
Classifier: License :: OSI Approved :: MIT License
Classifier: Operating System :: OS Independent
Classifier: Programming Language :: Python :: 3
Classifier: Programming Language :: Python :: 3.8
Classifier: Programming Language :: Python :: 3.9
Classifier: Programming Language :: Python :: 3.10
Classifier: Programming Language :: Python :: 3.11
Classifier: Programming Language :: Python :: 3.12
Classifier: Topic :: Software Development :: Libraries :: Python Modules
Classifier: Topic :: Software Development :: Quality Assurance
Classifier: Topic :: Software Development :: Testing
Classifier: Topic :: Utilities
Requires-Python: >=3.8
Provides-Extra: dev
Requires-Dist: black>=23.0; extra == 'dev'
Requires-Dist: mypy>=1.0; extra == 'dev'
Requires-Dist: pytest>=7.0; extra == 'dev'
Requires-Dist: ruff>=0.1.0; extra == 'dev'
